{
  "schema_version": 1,
  "status": "source-boundary-canonical-vectors",
  "canonical_serialization_test_vectors_finalized": true,
  "callable_ffi_implemented": false,
  "generated_bindings_claimed": false,
  "serialization_contract": [
    "deterministic_utf8_json_object",
    "explicit_schema_version",
    "sorted_keys",
    "string_enums",
    "bounded_status_label_arrays",
    "reject_unknown_fields"
  ],
  "status_dto_sorted_keys": [
    "backup_exclusion_state",
    "diagnostics_redaction_state",
    "install_update_integrity_state",
    "local_data_lifecycle_state",
    "mobile_command_surface",
    "platform",
    "profile_lock_state",
    "public_non_claims",
    "runtime_command_surface",
    "schema_version"
  ],
  "command_result_sorted_keys": [
    "failure_class",
    "recovery_next_action",
    "status"
  ],
  "vectors": {
    "shared_core_status_surface": "{\"backup_exclusion_state\":\"cloud backup not claimed\",\"diagnostics_redaction_state\":\"redacted status only\",\"install_update_integrity_state\":\"manual update verification required\",\"local_data_lifecycle_state\":\"app-private storage required\",\"mobile_command_surface\":[\"shared_core_status_surface\",\"redacted_support_diagnostics\"],\"platform\":\"android_shell_candidate\",\"profile_lock_state\":\"locked\",\"public_non_claims\":[\"unsigned experimental public beta\",\"sensitive communication prohibited\",\"not audited\",\"not production-ready\",\"external onion delivery not claimed\",\"security-ready not claimed\",\"mobile readiness not claimed\"],\"runtime_command_surface\":[\"shared_core_runtime_command_surface\"],\"schema_version\":1}",
    "redacted_support_diagnostics": "{\"backup_exclusion_state\":\"cloud backup not claimed\",\"diagnostics_redaction_state\":\"status/build/failure/recovery only\",\"install_update_integrity_state\":\"manual update verification required\",\"local_data_lifecycle_state\":\"local lifecycle status only\",\"mobile_command_surface\":[\"shared_core_status_surface\",\"redacted_support_diagnostics\"],\"platform\":\"android_shell_candidate\",\"profile_lock_state\":\"locked\",\"public_non_claims\":[\"unsigned experimental public beta\",\"sensitive communication prohibited\",\"not audited\",\"not production-ready\",\"external onion delivery not claimed\",\"security-ready not claimed\",\"mobile readiness not claimed\"],\"runtime_command_surface\":[\"shared_core_runtime_command_surface\"],\"schema_version\":1}",
    "blocked_command_result": "{\"failure_class\":\"policy_blocked\",\"recovery_next_action\":\"explicit user action required\",\"status\":\"blocked\"}",
    "lifecycle_confirmation_required_result": "{\"failure_class\":\"lifecycle_confirmation_required\",\"recovery_next_action\":\"confirm lifecycle intent before any shared Rust core binding for local_data_lifecycle\",\"status\":\"blocked\"}"
  },
  "reject_unknown_fields_vector": "{\"failure_class\":\"policy_blocked\",\"recovery_next_action\":\"explicit user action required\",\"status\":\"blocked\",\"unexpected\":\"reject\"}"
}
